flytekitplugins_dbt-1.16.12-py3.14-nspkg.pth
flytekitplugins/dbt/__init__.py
flytekitplugins/dbt/error.py
flytekitplugins/dbt/schema.py
flytekitplugins/dbt/task.py
flytekitplugins/dbt/util.py
flytekitplugins_dbt-1.16.12.dist-info/METADATA
flytekitplugins_dbt-1.16.12.dist-info/WHEEL
flytekitplugins_dbt-1.16.12.dist-info/namespace_packages.txt
flytekitplugins_dbt-1.16.12.dist-info/top_level.txt
flytekitplugins_dbt-1.16.12.dist-info/RECORD
